Cycle_1/Day_5_minimal-verilog/T_D_flipflop.v
module T_D_flipflop(
    input wire clk, rst, mode,
    output reg Q
);

always @(posedge clk or posedge rst) begin
if (rst)
Q<=0;
else if (mode == 0) // acting as T-flipflop
Q <= ~Q;
else if (mode == 1) // acting as D-flipflop
Q <= Q;
end
endmodule

Cycle_1/Day_5_minimal-verilog/tb_T_D_flipflop.v
`timescale 1ns/1ps

module tb_T_D_flipflop;
reg clk, rst, mode;
wire Q;

T_D_flipflop uut (.clk(clk), .rst(rst), .mode(mode), .Q(Q));

always #5 clk = ~clk;

initial begin
$dumpfile("T_D_flipflop.vcd");
$dumpvars(0,tb_T_D_flipflop);
clk = 0; rst=1;
#10;
clk = 1; rst = 0; mode = 0;
#50;
mode = 1;
#20;
mode = 0;
#20;
mode = 1;
#20;

$finish;
end
endmodule

Cycle_1/Day_5_minimal-verilog/T_D_flipflop.vcd
$date
	Mon Nov 10 20:13:25 2025
$end
$version
	Icarus Verilog
$end
$timescale
	1ps
$end
$scope module tb_T_D_flipflop $end
$var wire 1 ! Q $end
$var reg 1 " clk $end
$var reg 1 # mode $end
$var reg 1 $ rst $end
$scope module uut $end
$var wire 1 " clk $end
$var wire 1 # mode $end
$var wire 1 $ rst $end
$var reg 1 ! Q $end
$upscope $end
$upscope $end
$enddefinitions $end
#0
$dumpvars
1$
x#
0"
0!
$end
#5000
1"
#10000
0"
0#
0$
#15000
1!
1"
#20000
0"
#25000
0!
1"
#30000
0"
#35000
1!
1"
#40000
0"
#45000
0!
1"
#50000
0"
#55000
1!
1"
#60000
0"
1#
#65000
1"
#70000
0"
#75000
1"
#80000
0"
0#
#85000
0!
1"
#90000
0"
#95000
1!
1"
#100000
0"
1#
