Cycle_2/Day_1/shift_register.v
module shift_register #(
    parameter WIDTH = 8
)(
    input wire clk,
    input wire rst,
    input wire load,
    input wire [1:0] mode,   // 00 = hold, 01 = left shift, 10 = right shift
    input wire [WIDTH-1:0] data_in,
    output reg [WIDTH-1:0] q
);

always @(posedge clk or posedge rst) begin
    if (rst)
        q <= 0;

    else if (load)
        q <= data_in;

    else begin
        case (mode)
            2'b00: q <= q;                  // hold
            2'b01: q <= {q[WIDTH-2:0], 1'b0}; // left shift
            2'b10: q <= {1'b0, q[WIDTH-1:1]}; // right shift
            default: q <= q;
        endcase
    end
end

endmodule

Cycle_2/Day_1/tb_shift_register.v
`timescale 1ns/1ps
module tb_shift_register;

reg clk, rst, load;
reg [1:0] mode;
reg [7:0] data_in;
wire [7:0] q;

shift_register #(.WIDTH(8)) dut (
    .clk(clk), .rst(rst), .load(load),
    .mode(mode), .data_in(data_in), .q(q)
);

always #5 clk = ~clk;

initial begin
    $dumpfile("shift_reg.vcd");
    $dumpvars(0, tb_shift_register);

    clk=0; rst=1; load=0; mode=0; data_in=0;
    #12 rst=0;

    // load data
    load=1; data_in=8'b10110011; #10; load=0;

    // left shift
    mode=2'b01; #50;

    // right shift
    mode=2'b10; #50;

    // hold
    mode=2'b00; #20;

    $finish;
end

endmodule

Cycle_2/Day_1/shift_reg.vcd
$date
	Mon Nov 17 19:40:08 2025
$end
$version
	Icarus Verilog
$end
$timescale
	1ps
$end
$scope module tb_shift_register $end
$var wire 8 ! q [7:0] $end
$var reg 1 " clk $end
$var reg 8 # data_in [7:0] $end
$var reg 1 $ load $end
$var reg 2 % mode [1:0] $end
$var reg 1 & rst $end
$scope module dut $end
$var wire 1 " clk $end
$var wire 8 ' data_in [7:0] $end
$var wire 1 $ load $end
$var wire 2 ( mode [1:0] $end
$var wire 1 & rst $end
$var reg 8 ) q [7:0] $end
$upscope $end
$upscope $end
$enddefinitions $end
#0
$dumpvars
b0 )
b0 (
b0 '
1&
b0 %
0$
b0 #
0"
b0 !
$end
#5000
1"
#10000
0"
#12000
b10110011 #
b10110011 '
1$
0&
#15000
b10110011 !
b10110011 )
1"
#20000
0"
#22000
b1 %
b1 (
0$
#25000
b1100110 !
b1100110 )
1"
#30000
0"
#35000
b11001100 !
b11001100 )
1"
#40000
0"
#45000
b10011000 !
b10011000 )
1"
#50000
0"
#55000
b110000 !
b110000 )
1"
#60000
0"
#65000
b1100000 !
b1100000 )
1"
#70000
0"
#72000
b10 %
b10 (
#75000
b110000 !
b110000 )
1"
#80000
0"
#85000
b11000 !
b11000 )
1"
#90000
0"
#95000
b1100 !
b1100 )
1"
#100000
0"
#105000
b110 !
b110 )
1"
#110000
0"
#115000
b11 !
b11 )
1"
#120000
0"
#122000
b0 %
b0 (
