Cycle_1/Day_6.2/counter_4bit.v
module counter_4bit(
    input wire clk,
    input wire rst,
    input wire mode,          // 0=Up, 1=Down
    output reg [3:0] count
);
always @(posedge clk or posedge rst) begin
    if (rst)
        count <= 4'b0000;
    else begin
        if (mode == 1'b0)           // Up
            count <= count + 1'b1;
        else                        // Down
            count <= count - 1'b1;
    end
end
endmodule

Cycle_1/Day_6.2/tb_counter_4bit.v
`timescale 1ns/1ps
module tb_counter_4bit;
reg clk, rst, mode;
wire [3:0] count;

counter_4bit uut (.clk(clk), .rst(rst), .mode(mode), .count(count));

always #5 clk = ~clk;   // 10 ns clock period

initial begin
  $dumpfile("counter_4bit.vcd");
  $dumpvars(0, tb_counter_4bit);
  clk=0; rst=1; mode=0;
  #12 rst=0;
  #100 mode=1;        // switch to down-count
  #80  mode=0;        // back to up
  #60  $finish;
end

initial $monitor("t=%0t | mode=%b | count=%b", $time, mode, count);
endmodule

Cycle_1/Day_6.2/counter_4bit.vcd
$date
	Thu Nov 13 19:00:08 2025
$end
$version
	Icarus Verilog
$end
$timescale
	1ps
$end
$scope module tb_counter_4bit $end
$var wire 4 ! count [3:0] $end
$var reg 1 " clk $end
$var reg 1 # mode $end
$var reg 1 $ rst $end
$scope module uut $end
$var wire 1 " clk $end
$var wire 1 # mode $end
$var wire 1 $ rst $end
$var reg 4 % count [3:0] $end
$upscope $end
$upscope $end
$enddefinitions $end
#0
$dumpvars
b0 %
1$
0#
0"
b0 !
$end
#5000
1"
#10000
0"
#12000
0$
#15000
b1 !
b1 %
1"
#20000
0"
#25000
b10 !
b10 %
1"
#30000
0"
#35000
b11 !
b11 %
1"
#40000
0"
#45000
b100 !
b100 %
1"
#50000
0"
#55000
b101 !
b101 %
1"
#60000
0"
#65000
b110 !
b110 %
1"
#70000
0"
#75000
b111 !
b111 %
1"
#80000
0"
#85000
b1000 !
b1000 %
1"
#90000
0"
#95000
b1001 !
b1001 %
1"
#100000
0"
#105000
b1010 !
b1010 %
1"
#110000
0"
#112000
1#
#115000
b1001 !
b1001 %
1"
#120000
0"
#125000
b1000 !
b1000 %
1"
#130000
0"
#135000
b111 !
b111 %
1"
#140000
0"
#145000
b110 !
b110 %
1"
#150000
0"
#155000
b101 !
b101 %
1"
#160000
0"
#165000
b100 !
b100 %
1"
#170000
0"
#175000
b11 !
b11 %
1"
#180000
0"
#185000
b10 !
b10 %
1"
#190000
0"
#192000
0#
#195000
b11 !
b11 %
1"
#200000
0"
#205000
b100 !
b100 %
1"
#210000
0"
#215000
b101 !
b101 %
1"
#220000
0"
#225000
b110 !
b110 %
1"
#230000
0"
#235000
b111 !
b111 %
1"
#240000
0"
#245000
b1000 !
b1000 %
1"
